<?xml version="1.0" encoding="UTF-8"?><customers><identification><author name="Michael Minella"></author></identification><customer><id>31</id><firstName>Jacqueline</firstName><middleInitial>E</middleInitial><lastName>Savage</lastName><address>2364 Imperdiet Street</address><city>Tulsa</city><state>OK</state></customer><customer><id>32</id><firstName>Yasir</firstName><middleInitial>F</middleInitial><lastName>White</lastName><address>P.O. Box 744, 8135 Viverra. Rd.</address><city>Bellevue</city><state>NE</state></customer><customer><id>33</id><firstName>Nigel</firstName><middleInitial>G</middleInitial><lastName>Maynard</lastName><address>301-5143 Pretium Ave</address><city>Columbus</city><state>OH</state></customer><customer><id>34</id><firstName>Cullen</firstName><middleInitial>H</middleInitial><lastName>Rosario</lastName><address>P.O. Box 420, 1827 Cras Street</address><city>Cambridge</city><state>MA</state></customer><customer><id>35</id><firstName>Juliet</firstName><middleInitial>I</middleInitial><lastName>Woodard</lastName><address>622-3134 Feugiat Road</address><city>St. Petersburg</city><state>FL</state></customer><customer><id>36</id><firstName>Glenna</firstName><middleInitial>J</middleInitial><lastName>Roth</lastName><address>3293 Faucibus Ave</address><city>Bangor</city><state>ME</state></customer><customer><id>37</id><firstName>Gannon</firstName><middleInitial>K</middleInitial><lastName>Roberson</lastName><address>Ap #684-6001 Sociosqu Road</address><city>Butte</city><state>MT</state></customer><customer><id>38</id><firstName>Derek</firstName><middleInitial>L</middleInitial><lastName>Burnett</lastName><address>P.O. Box 134, 662 Imperdiet St.</address><city>Georgia</city><state>GA</state></customer><customer><id>39</id><firstName>Gage</firstName><middleInitial>M</middleInitial><lastName>Velazquez</lastName><address>644-1262 Donec Av.</address><city>Fayetteville</city><state>AR</state></customer><customer><id>40</id><firstName>Allen</firstName><middleInitial>N</middleInitial><lastName>Bernard</lastName><address>Ap #665-6648 At, Ave</address><city>Oklahoma City</city><state>OK</state></customer><customer><id>41</id><firstName>Zeus</firstName><middleInitial>O</middleInitial><lastName>Bray</lastName><address>P.O. Box 791, 9813 Tellus. St.</address><city>Grand Island</city><state>NE</state></customer><customer><id>42</id><firstName>Hedy</firstName><middleInitial>P</middleInitial><lastName>Mccray</lastName><address>981 Porttitor Rd.</address><city>Norfolk</city><state>VA</state></customer><customer><id>43</id><firstName>Cherokee</firstName><middleInitial>Q</middleInitial><lastName>Le</lastName><address>750-1609 Ultricies Road</address><city>Erie</city><state>PA</state></customer><customer><id>44</id><firstName>Joelle</firstName><middleInitial>R</middleInitial><lastName>Stephens</lastName><address>2844 Tempus Road</address><city>Virginia Beach</city><state>VA</state></customer><customer><id>45</id><firstName>Shelly</firstName><middleInitial>S</middleInitial><lastName>Ferguson</lastName><address>P.O. Box 595, 7847 Aliquam Street</address><city>Kansas City</city><state>MO</state></customer><customer><id>46</id><firstName>Jason</firstName><middleInitial>T</middleInitial><lastName>Cooper</lastName><address>629-5463 Massa. St.</address><city>Fairbanks</city><state>AK</state></customer><customer><id>47</id><firstName>Dante</firstName><middleInitial>U</middleInitial><lastName>Emerson</lastName><address>P.O. Box 669, 7540 Risus, Avenue</address><city>Jackson</city><state>MS</state></customer><customer><id>48</id><firstName>Eaton</firstName><middleInitial>V</middleInitial><lastName>Baxter</lastName><address>871-2281 Magna St.</address><city>South Portland</city><state>ME</state></customer><customer><id>49</id><firstName>Amanda</firstName><middleInitial>W</middleInitial><lastName>Villarreal</lastName><address>1599 Ac Rd.</address><city>Cambridge</city><state>MA</state></customer><customer><id>50</id><firstName>Chancellor</firstName><middleInitial>X</middleInitial><lastName>Dillard</lastName><address>P.O. Box 418, 4453 Auctor St.</address><city>Allentown</city><state>PA</state></customer><customer><id>51</id><firstName>Cynthia</firstName><middleInitial>Y</middleInitial><lastName>Farmer</lastName><address>P.O. Box 540, 3785 Eu Av.</address><city>Fort Worth</city><state>TX</state></customer><customer><id>52</id><firstName>Lilah</firstName><middleInitial>Z</middleInitial><lastName>Mills</lastName><address>P.O. Box 111, 1738 Dapibus St.</address><city>Helena</city><state>MT</state></customer><customer><id>53</id><firstName>Malachi</firstName><middleInitial>A</middleInitial><lastName>Blanchard</lastName><address>870-382 Ante St.</address><city>Mesa</city><state>AZ</state></customer><customer><id>54</id><firstName>Kyle</firstName><middleInitial>B</middleInitial><lastName>Mack</lastName><address>Ap #712-5837 Suspendisse St.</address><city>Cincinnati</city><state>OH</state></customer><customer><id>55</id><firstName>Rigel</firstName><middleInitial>C</middleInitial><lastName>Dodson</lastName><address>579-5256 Mattis Avenue</address><city>Laramie</city><state>WY</state></customer><customer><id>56</id><firstName>Lilah</firstName><middleInitial>D</middleInitial><lastName>Hensley</lastName><address>Ap #839-3725 Tempor Ave</address><city>Cambridge</city><state>MA</state></customer><customer><id>57</id><firstName>Hope</firstName><middleInitial>E</middleInitial><lastName>Tyson</lastName><address>651-2173 Egestas. St.</address><city>Gillette</city><state>WY</state></customer><customer><id>58</id><firstName>Erich</firstName><middleInitial>F</middleInitial><lastName>Holder</lastName><address>260-6930 Pharetra, Rd.</address><city>Fresno</city><state>CA</state></customer><customer><id>59</id><firstName>Lila</firstName><middleInitial>G</middleInitial><lastName>Kirk</lastName><address>P.O. Box 610, 6587 A, Rd.</address><city>Boston</city><state>MA</state></customer><customer><id>60</id><firstName>Jessica</firstName><middleInitial>H</middleInitial><lastName>Green</lastName><address>429-4635 Placerat, Road</address><city>Southaven</city><state>MS</state></customer></customers>