<?xml version="1.0" encoding="UTF-8"?><customers><identification><author name="Michael Minella"></author></identification><customer><id>211</id><firstName>Thomas</firstName><middleInitial>C</middleInitial><lastName>Payne</lastName><address>Ap #544-1590 Nulla Street</address><city>Georgia</city><state>GA</state></customer><customer><id>212</id><firstName>Arsenio</firstName><middleInitial>D</middleInitial><lastName>Fox</lastName><address>Ap #449-9718 Dui Avenue</address><city>Chandler</city><state>AZ</state></customer><customer><id>213</id><firstName>Morgan</firstName><middleInitial>E</middleInitial><lastName>Arnold</lastName><address>833-5886 In Av.</address><city>Fort Wayne</city><state>IN</state></customer><customer><id>214</id><firstName>Blake</firstName><middleInitial>F</middleInitial><lastName>Klein</lastName><address>351-1040 Convallis Av.</address><city>Covington</city><state>KY</state></customer><customer><id>215</id><firstName>Heather</firstName><middleInitial>G</middleInitial><lastName>Bernard</lastName><address>P.O. Box 253, 1957 Eu St.</address><city>Spokane</city><state>WA</state></customer><customer><id>216</id><firstName>Jarrod</firstName><middleInitial>H</middleInitial><lastName>Goff</lastName><address>219-6060 Viverra. Street</address><city>Cedar Rapids</city><state>IA</state></customer><customer><id>217</id><firstName>Blaze</firstName><middleInitial>I</middleInitial><lastName>Hutchinson</lastName><address>P.O. Box 596, 6602 A Street</address><city>Boise</city><state>ID</state></customer><customer><id>218</id><firstName>Eaton</firstName><middleInitial>J</middleInitial><lastName>Olsen</lastName><address>603-2755 Etiam St.</address><city>Birmingham</city><state>AL</state></customer><customer><id>219</id><firstName>Talon</firstName><middleInitial>K</middleInitial><lastName>Sanders</lastName><address>Ap #521-2519 Dignissim Road</address><city>Jackson</city><state>MS</state></customer><customer><id>220</id><firstName>Knox</firstName><middleInitial>L</middleInitial><lastName>Chase</lastName><address>P.O. Box 143, 8492 Nec, St.</address><city>Bellevue</city><state>NE</state></customer><customer><id>221</id><firstName>Walter</firstName><middleInitial>M</middleInitial><lastName>Glover</lastName><address>Ap #594-5748 In, Ave</address><city>Philadelphia</city><state>PA</state></customer><customer><id>222</id><firstName>Harrison</firstName><middleInitial>N</middleInitial><lastName>Zamora</lastName><address>903-322 Nulla. Rd.</address><city>Reno</city><state>NV</state></customer><customer><id>223</id><firstName>Cedric</firstName><middleInitial>O</middleInitial><lastName>Franks</lastName><address>Ap #203-8482 Mauris Rd.</address><city>Dallas</city><state>TX</state></customer><customer><id>224</id><firstName>Hedda</firstName><middleInitial>P</middleInitial><lastName>Key</lastName><address>7691 Eleifend St.</address><city>Wichita</city><state>KS</state></customer><customer><id>225</id><firstName>Olivia</firstName><middleInitial>Q</middleInitial><lastName>Clements</lastName><address>Ap #234-1568 Sed Street</address><city>Harrisburg</city><state>PA</state></customer><customer><id>226</id><firstName>Maggy</firstName><middleInitial>R</middleInitial><lastName>Hale</lastName><address>P.O. Box 599, 175 Scelerisque St.</address><city>Bellevue</city><state>NE</state></customer><customer><id>227</id><firstName>Shay</firstName><middleInitial>S</middleInitial><lastName>Collier</lastName><address>704-2183 At, Av.</address><city>Austin</city><state>TX</state></customer><customer><id>228</id><firstName>Cameron</firstName><middleInitial>T</middleInitial><lastName>Jacobs</lastName><address>5405 Ac Ave</address><city>Bellevue</city><state>NE</state></customer><customer><id>229</id><firstName>Joseph</firstName><middleInitial>U</middleInitial><lastName>Battle</lastName><address>P.O. Box 841, 9599 Consectetuer, St.</address><city>Chesapeake</city><state>VA</state></customer><customer><id>230</id><firstName>Astra</firstName><middleInitial>V</middleInitial><lastName>Estrada</lastName><address>P.O. Box 808, 7208 Nec Avenue</address><city>Stamford</city><state>CT</state></customer><customer><id>231</id><firstName>John</firstName><middleInitial>W</middleInitial><lastName>Pearson</lastName><address>4531 Sed St.</address><city>Wichita</city><state>KS</state></customer><customer><id>232</id><firstName>Kimberley</firstName><middleInitial>X</middleInitial><lastName>Bush</lastName><address>P.O. Box 614, 2932 Pede. Rd.</address><city>Rock Springs</city><state>WY</state></customer><customer><id>233</id><firstName>Belle</firstName><middleInitial>Y</middleInitial><lastName>York</lastName><address>709-1516 Eu, Av.</address><city>Dover</city><state>DE</state></customer><customer><id>234</id><firstName>Wynter</firstName><middleInitial>Z</middleInitial><lastName>Vazquez</lastName><address>Ap #399-1383 Fermentum Road</address><city>Springdale</city><state>AR</state></customer><customer><id>235</id><firstName>Quintessa</firstName><middleInitial>A</middleInitial><lastName>Kemp</lastName><address>139 Ultrices. Rd.</address><city>Kailua</city><state>HI</state></customer><customer><id>236</id><firstName>Christine</firstName><middleInitial>B</middleInitial><lastName>Beard</lastName><address>5201 Consequat, Av.</address><city>Louisville</city><state>KY</state></customer><customer><id>237</id><firstName>Perry</firstName><middleInitial>C</middleInitial><lastName>Wilkerson</lastName><address>Ap #825-7040 Rutrum Street</address><city>College</city><state>AK</state></customer><customer><id>238</id><firstName>Veronica</firstName><middleInitial>D</middleInitial><lastName>Snyder</lastName><address>4071 Dignissim Rd.</address><city>Lewiston</city><state>ME</state></customer><customer><id>239</id><firstName>Josephine</firstName><middleInitial>E</middleInitial><lastName>Franklin</lastName><address>361-4243 Sit Avenue</address><city>Richmond</city><state>VA</state></customer><customer><id>240</id><firstName>Dane</firstName><middleInitial>F</middleInitial><lastName>Jacobs</lastName><address>Ap #825-2231 Odio St.</address><city>Los Angeles</city><state>CA</state></customer></customers>